driviz/__init__.py
driviz/theme.py
driviz-0.6.1.dist-info/METADATA
driviz-0.6.1.dist-info/WHEEL
driviz-0.6.1.dist-info/licenses/LICENSE
driviz-0.6.1.dist-info/RECORD
