Metadata-Version: 2.4
Name: driviz
Version: 0.6.1
Summary: Data Visualization Library containing the Dribia Theme.
Project-URL: Homepage, https://github.com/dribia/driviz
Project-URL: Repository, https://github.com/dribia/driviz
Author-email: Dribia Data Research <code@dribia.com>
Maintainer-email: Dribia Data Research <code@dribia.com>
License-Expression: MIT
License-File: LICENSE
Classifier: Intended Audience :: Developers
Classifier: License :: OSI Approved :: MIT License
Classifier: Operating System :: OS Independent
Classifier: Programming Language :: Python
Classifier: Programming Language :: Python :: 3
Classifier: Programming Language :: Python :: 3 :: Only
Classifier: Programming Language :: Python :: 3.10
Classifier: Programming Language :: Python :: 3.11
Classifier: Programming Language :: Python :: 3.12
Classifier: Programming Language :: Python :: 3.13
Classifier: Programming Language :: Python :: 3.14
Classifier: Topic :: Internet
Classifier: Topic :: Software Development
Classifier: Topic :: Software Development :: Libraries
Classifier: Topic :: Software Development :: Libraries :: Python Modules
Classifier: Typing :: Typed
Requires-Python: <3.15,>=3.10
Requires-Dist: altair<7,>=5.5.0
Requires-Dist: cycler<0.13,>=0.12.1
Requires-Dist: matplotlib<4,>=3.9.2
Requires-Dist: numpy<3.0,>=1.26
Requires-Dist: pydantic-extra-types<3,>=2.10.0
Requires-Dist: pydantic<3,>=2.9.0
Requires-Dist: vl-convert-python==1.8.0
